opencdms_test_databases/__init__.py
opencdms_test_databases/cli.py
opencdms_test_databases/config.py
opencdms_test_databases/docker-compose.yml
opencdms_test_databases/conf/postgres.conf
opencdms_test_databases/docker/Dockerfile
opencdms_test_databases/docker/Dockerfile.clide
opencdms_test_databases/docker/Dockerfile.climsoft-4.1.1
opencdms_test_databases/docker/Dockerfile.mch-english
opencdms_test_databases/docker/Dockerfile.midas
opencdms_test_databases/docker/Dockerfile.surface
opencdms_test_databases/docker/Dockerfile.wmdr
opencdms_test_databases/docker/groups/Dockerfile.mysql
opencdms_test_databases/docker/groups/Dockerfile.oracle
opencdms_test_databases/docker/groups/Dockerfile.postgresql
opencdms_test_databases/schemas/README.md
opencdms_test_databases/schemas/adam/README.md
opencdms_test_databases/schemas/bdclim/MF_GT_CLIMAT_BDCLIM_structure.pdf
opencdms_test_databases/schemas/bdclim/README.md
opencdms_test_databases/schemas/cdm-obs/.gitkeep
opencdms_test_databases/schemas/clide/README.md
opencdms_test_databases/schemas/clide/clidedb_schema.sql
opencdms_test_databases/schemas/clide/obs_daily.md
opencdms_test_databases/schemas/climsoft/v4/LICENSE
opencdms_test_databases/schemas/climsoft/v4/docs/CLIMSOFT_v4_technical_requirements_update_uploaded.pdf
opencdms_test_databases/schemas/climsoft/v4/docs/climsoft4_Technical_Requirements_v1.0.docx
opencdms_test_databases/schemas/climsoft/v4/docs/climsoft4_element_codes.xls
opencdms_test_databases/schemas/climsoft/v4/v4.1.1/README.md
opencdms_test_databases/schemas/climsoft/v4/v4.1.1/climsoft_v4_all.sql
opencdms_test_databases/schemas/climsoft/v4/v4.1.1/climsoft_v4_empty_db_only.sql
opencdms_test_databases/schemas/climsoft/v4/v4.1.1/climsoft_v4_test_data_only.sql
opencdms_test_databases/schemas/climsoft/v4/v4.1.1/observationfinal.md
opencdms_test_databases/schemas/climsoft/v4/v4.1.1/station.md
opencdms_test_databases/schemas/climsoft/v5/docs/design.md
opencdms_test_databases-0.1.10.dist-info/LICENSE
opencdms_test_databases-0.1.10.dist-info/METADATA
opencdms_test_databases-0.1.10.dist-info/WHEEL
opencdms_test_databases-0.1.10.dist-info/top_level.txt
opencdms_test_databases-0.1.10.dist-info/RECORD
